liner/LICENSE
liner/README.md
liner/__init__.py
liner/__main__.py
liner/libliner.cp39.so
liner/liner.abi3.so
liner/start.c
liner_py-1600.dist-info/METADATA
liner_py-1600.dist-info/WHEEL
liner_py-1600.dist-info/top_level.txt
liner_py-1600.dist-info/RECORD
