Metadata-Version: 2.4
Name: liner-py
Version: 1600
Summary: python bindings for liner
Home-page: https://github.com/phuslu/liner
Author: Phus Lu
Author-email: phus.lu@gmail.com
License: AGPL-3.0
Classifier: Programming Language :: Python :: 3
Classifier: License :: OSI Approved :: MIT License
Requires-Python: >=3.9
Dynamic: author
Dynamic: author-email
Dynamic: classifier
Dynamic: description
Dynamic: description-content-type
Dynamic: home-page
Dynamic: license
Dynamic: requires-python
Dynamic: summary
